grilops/__init__.py
grilops/fastz3.py
grilops/geometry.py
grilops/grids.py
grilops/loops.py
grilops/paths.py
grilops/quadtree.py
grilops/regions.py
grilops/shapes.py
grilops/sightlines.py
grilops/symbols.py
grilops-0.10.3.dist-info/LICENSE
grilops-0.10.3.dist-info/METADATA
grilops-0.10.3.dist-info/WHEEL
grilops-0.10.3.dist-info/top_level.txt
grilops-0.10.3.dist-info/RECORD
