Metadata-Version: 2.1
Name: grilops
Version: 0.10.3
Summary: GRId LOgic Puzzle Solver
Home-page: https://github.com/obijywk/grilops
Author: Matt Gruskin
Author-email: matthew.gruskin@gmail.com
License: MIT
Requires-Python: >=3.6
License-File: LICENSE
Requires-Dist: z3-solver
